rttm_manager/__init__.py
rttm_manager/entity/rttm.py
rttm_manager/service/exporter.py
rttm_manager/service/importer.py
rttm_manager-0.1.8.dist-info/METADATA
rttm_manager-0.1.8.dist-info/WHEEL
rttm_manager-0.1.8.dist-info/RECORD
