Metadata-Version: 2.3
Name: rttm_manager
Version: 0.1.8
Summary: Add your description here
Author-email: kittchy <drums.radwimps203@gmail.com>
Requires-Python: >=3.10
Requires-Dist: pydantic>=2.7.0
